rusted.py
rusted-0.1.0.dist-info/DESCRIPTION.rst
rusted-0.1.0.dist-info/METADATA
rusted-0.1.0.dist-info/RECORD
rusted-0.1.0.dist-info/WHEEL
rusted-0.1.0.dist-info/entry_points.txt
rusted-0.1.0.dist-info/metadata.json
rusted-0.1.0.dist-info/top_level.txt
